tox_block/VERSION
tox_block/__init__.py
tox_block/prediction.py
tox_block/training_pipeline.py
tox_block/config/__init__.py
tox_block/config/config.py
tox_block/config/logging_config.py
tox_block/data/__init__.py
tox_block/data_processing/__init__.py
tox_block/data_processing/data_handling.py
tox_block/data_processing/preprocessors.py
tox_block/model/__init__.py
tox_block/model/lstm_multi_label.py
tox_block/trained_models/__init__.py
tox_block/trained_models/encoder_0.1.2.pkl
tox_block/trained_models/lstm_model_0.1.2.h5
tox_block/trained_models/lstm_model_training_history_0.1.2.pkl
tox_block-0.1.2.dist-info/LICENSE
tox_block-0.1.2.dist-info/METADATA
tox_block-0.1.2.dist-info/WHEEL
tox_block-0.1.2.dist-info/top_level.txt
tox_block-0.1.2.dist-info/RECORD
