Metadata-Version: 2.1
Name: tox-block
Version: 0.1.2
Summary: This is a python package for classifying text in 6 categories of verbal toxicity using deep learning.
Home-page: https://github.com/Pascal-Bliem/tox-block
Author: Pascal Bliem
Author-email: pascal@bliem.de
License: MIT
Platform: UNKNOWN
Classifier: License :: OSI Approved :: MIT License
Classifier: Programming Language :: Python
Classifier: Programming Language :: Python :: 3
Classifier: Programming Language :: Python :: 3.7
Classifier: Programming Language :: Python :: 3.8
Classifier: Programming Language :: Python :: Implementation :: CPython
Classifier: Programming Language :: Python :: Implementation :: PyPy
Classifier: Natural Language :: English
Classifier: Operating System :: OS Independent
Requires-Python: >=3.7.0
Requires-Dist: joblib (>=0.15.1)
Requires-Dist: numpy (>=1.18.1)
Requires-Dist: pandas (>=1.0.3)
Requires-Dist: scikit-learn (>=0.22.1)
Requires-Dist: tensorflow (>=2.1.0)
